client_gpt/__init__.py
client_gpt/client_gpt.py
client_GPT-2.1.0.dist-info/METADATA
client_GPT-2.1.0.dist-info/WHEEL
client_GPT-2.1.0.dist-info/top_level.txt
client_GPT-2.1.0.dist-info/RECORD
