Metadata-Version: 2.1
Name: client-GPT
Version: 2.1.0
Summary: A package for working with GPT language models.
Home-page: https://github.com/littleknitsstory/client-gpt
Author: littleknitsstory
Classifier: Development Status :: 3 - Alpha
Classifier: Intended Audience :: Developers
Classifier: Topic :: Software Development :: Libraries
Classifier: Programming Language :: Python :: 3
Requires-Python: >=3.6
Requires-Dist: requests
